CHANGES.txt
LICENSE.txt
MANIFEST.in
README.txt
requirements.txt
setup.py
dhl_shipping/__init__.py
dhl_shipping/admin.py
dhl_shipping/apps.py
dhl_shipping/common.py
dhl_shipping/config.py
dhl_shipping/dhl_process.py
dhl_shipping/models.py
dhl_shipping/pickup.py
dhl_shipping/quote.py
dhl_shipping/shipment.py
dhl_shipping/tests.py
dhl_shipping/views.py
dhl_shipping.egg-info/.DS_Store
dhl_shipping.egg-info/PKG-INFO
dhl_shipping.egg-info/SOURCES.txt
dhl_shipping.egg-info/dependency_links.txt
dhl_shipping.egg-info/pbr.json
dhl_shipping.egg-info/requires.txt
dhl_shipping.egg-info/top_level.txt