Metadata-Version: 1.1
Name: dhl-shipping
Version: 2.0.5
Summary: DHL Shipping - Quote, Pick Up, Shipping, Label Creation, Tracking
Home-page: http://pypi.python.org/pypi/dhl_shipping/
Author: Hasanuzzaman Syed
Author-email: hasanuzzaman.syed@gmail.com
License: LICENSE.txt
Platform: UNKNOWN
Classifier: Development Status :: 5 - Production/Stable
Classifier: Intended Audience :: Developers
Classifier: Programming Language :: Python
Classifier: Programming Language :: Python :: Implementation :: PyPy
Classifier: Topic :: Software Development :: Libraries :: Python Modules
